furlan_g2p/__about__.py
furlan_g2p/__init__.py
furlan_g2p/main.py
furlan_g2p/cli/__init__.py
furlan_g2p/cli/app.py
furlan_g2p/config/__init__.py
furlan_g2p/config/schemas.py
furlan_g2p/core/__init__.py
furlan_g2p/core/exceptions.py
furlan_g2p/core/interfaces.py
furlan_g2p/core/types.py
furlan_g2p/data/__init__.py
furlan_g2p/data/seed_lexicon.tsv
furlan_g2p/g2p/__init__.py
furlan_g2p/g2p/lexicon.py
furlan_g2p/g2p/phonemizer.py
furlan_g2p/g2p/rules.py
furlan_g2p/normalization/__init__.py
furlan_g2p/normalization/normalizer.py
furlan_g2p/phonology/__init__.py
furlan_g2p/phonology/inventory.py
furlan_g2p/phonology/ipa.py
furlan_g2p/phonology/stress.py
furlan_g2p/phonology/syllabifier.py
furlan_g2p/services/__init__.py
furlan_g2p/services/io_service.py
furlan_g2p/services/pipeline.py
furlan_g2p/tokenization/__init__.py
furlan_g2p/tokenization/tokenizer.py
furlang2p-0.1.0.dist-info/METADATA
furlang2p-0.1.0.dist-info/WHEEL
furlang2p-0.1.0.dist-info/entry_points.txt
furlang2p-0.1.0.dist-info/licenses/LICENSE
furlang2p-0.1.0.dist-info/RECORD
