Metadata-Version: 2.4
Name: furlang2p
Version: 0.1.0
Summary: Friulian text normalization, tokenization, G2P conversion and phonology with a CLI and pipeline service.
Project-URL: Homepage, https://github.com/daurmax/FurlanG2P
Project-URL: Issues, https://github.com/daurmax/FurlanG2P/issues
Author-email: Massimo Romanin <dev@massimoromanin.com>
License: Attribution-NonCommercial 4.0 International
License-File: LICENSE
Keywords: g2p,nlp,phonemization,text-normalization,tts
Classifier: License :: Free for non-commercial use
Classifier: License :: Other/Proprietary License
Classifier: Operating System :: OS Independent
Classifier: Programming Language :: Python :: 3
Classifier: Programming Language :: Python :: 3 :: Only
Requires-Python: >=3.10
Requires-Dist: click>=8.1.7
Provides-Extra: dev
Requires-Dist: black>=24.4.0; extra == 'dev'
Requires-Dist: hypothesis>=6.0.0; extra == 'dev'
Requires-Dist: mypy>=1.10.0; extra == 'dev'
Requires-Dist: pytest-cov>=4.1.0; extra == 'dev'
Requires-Dist: pytest>=8.0.0; extra == 'dev'
Requires-Dist: pyyaml>=6.0; extra == 'dev'
Requires-Dist: ruff>=0.5.0; extra == 'dev'
Requires-Dist: types-click>=7.1.8; extra == 'dev'
